chalice/__init__.py
chalice/analyzer.py
chalice/app.py
chalice/awsclient.py
chalice/compat.py
chalice/config.py
chalice/constants.py
chalice/invoke.py
chalice/local.py
chalice/logs.py
chalice/package.py
chalice/pipeline.py
chalice/policies-extra.json
chalice/policies.json
chalice/policy.py
chalice/utils.py
chalice/cli/__init__.py
chalice/cli/factory.py
chalice/cli/reloader.py
chalice/cli/filewatch/__init__.py
chalice/cli/filewatch/eventbased.py
chalice/cli/filewatch/stat.py
chalice/deploy/__init__.py
chalice/deploy/deployer.py
chalice/deploy/executor.py
chalice/deploy/models.py
chalice/deploy/packager.py
chalice/deploy/planner.py
chalice/deploy/swagger.py
chalice/deploy/sweeper.py
chalice/deploy/validate.py
mod_chalice-1.0.dist-info/DESCRIPTION.rst
mod_chalice-1.0.dist-info/METADATA
mod_chalice-1.0.dist-info/RECORD
mod_chalice-1.0.dist-info/WHEEL
mod_chalice-1.0.dist-info/entry_points.txt
mod_chalice-1.0.dist-info/metadata.json
mod_chalice-1.0.dist-info/top_level.txt
tests/aws/__init__.py
tests/aws/conftest.py
tests/aws/test_features.py
tests/aws/test_websockets.py
tests/functional/__init__.py
tests/functional/conftest.py
tests/functional/test_awsclient.py
tests/functional/test_deployer.py
tests/functional/test_local.py
tests/functional/test_package.py
tests/functional/test_utils.py
tests/functional/cli/__init__.py
tests/functional/cli/test_cli.py
tests/functional/cli/test_factory.py
tests/functional/cli/test_reloader.py
tests/integration/__init__.py
tests/integration/test_cli.py
tests/integration/test_package.py
tests/unit/__init__.py
tests/unit/conftest.py
tests/unit/test_analyzer.py
tests/unit/test_app.py
tests/unit/test_config.py
tests/unit/test_invoke.py
tests/unit/test_local.py
tests/unit/test_logs.py
tests/unit/test_package.py
tests/unit/test_pipeline.py
tests/unit/test_policy.py
tests/unit/test_utils.py
tests/unit/cli/__init__.py
tests/unit/cli/test_cli.py
tests/unit/deploy/__init__.py
tests/unit/deploy/test_deployer.py
tests/unit/deploy/test_executor.py
tests/unit/deploy/test_models.py
tests/unit/deploy/test_packager.py
tests/unit/deploy/test_planner.py
tests/unit/deploy/test_swagger.py
tests/unit/deploy/test_validate.py
