Metadata-Version: 2.0
Name: mod-chalice
Version: 1.0
Summary: Microframework
Home-page: https://github.com/rapdus/chalice
Author: Dushyant Rajput
Author-email: rajpdus@gmail.com
License: Apache License 2.0
Keywords: chalice
Platform: UNKNOWN
Classifier: Development Status :: 5 - Production/Stable
Classifier: Intended Audience :: Developers
Classifier: License :: OSI Approved :: Apache Software License
Classifier: Natural Language :: English
Classifier: Programming Language :: Python :: 2
Classifier: Programming Language :: Python :: 2.7
Classifier: Programming Language :: Python :: 3.6
Classifier: Programming Language :: Python :: 3.7
Provides-Extra: event-file-poller
Requires-Dist: attrs (>=17.4.0,<20.0.0)
Requires-Dist: botocore (<2.0.0,>=1.12.86)
Requires-Dist: click (<8.0,>=6.6)
Requires-Dist: enum-compat (>=0.0.2)
Requires-Dist: jmespath (>=0.9.3,<1.0.0)
Requires-Dist: pip (<19.4,>=9)
Requires-Dist: setuptools
Requires-Dist: six (<2.0.0,>=1.10.0)
Requires-Dist: wheel
Requires-Dist: typing (==3.6.4); python_version < "3.7"
Provides-Extra: event-file-poller
Requires-Dist: watchdog (==0.8.3); extra == 'event-file-poller'
